qiskit_basis_constructor/__init__.py
qiskit_basis_constructor/constructor.py
qiskit_basis_constructor/equivalence.py
qiskit_basis_constructor/plugin.py
qiskit_basis_constructor-0.1.0.dist-info/METADATA
qiskit_basis_constructor-0.1.0.dist-info/WHEEL
qiskit_basis_constructor-0.1.0.dist-info/entry_points.txt
qiskit_basis_constructor-0.1.0.dist-info/licenses/LICENSE.txt
qiskit_basis_constructor-0.1.0.dist-info/RECORD
