Metadata-Version: 2.4
Name: qiskit-basis-constructor
Version: 0.1.0
Summary: Translation plugin for the Qiskit transpiler based on a graph-search construction of the source basis from the target.
Author-email: Jake Lishman <jake.lishman@ibm.com>, Qiskit Development Team <qiskit@us.ibm.com>
License:                                  Apache License
License-File: LICENSE.txt
Classifier: Intended Audience :: Developers
Classifier: Intended Audience :: Science/Research
Classifier: License :: OSI Approved :: Apache Software License
Classifier: Topic :: Scientific/Engineering
Requires-Python: >=3.9
Requires-Dist: qiskit>=1.3.0
Requires-Dist: rustworkx>=0.14.0
